{"cameraMode":{"drawMode":0,"name":"Shaded","section":"Shading Mode"},"sceneLighting":true,"audioPlay":false,"sceneViewState":{"m_AlwaysRefresh":false,"showFog":true,"showSkybox":true,"showFlares":true,"showImageEffects":true,"showParticleSystems":true,"showVisualEffectGraphs":true,"m_FxEnabled":false},"in2DMode":false,"pivot":{"x":357.3056640625,"y":0.6913464665412903,"z":236.27098083496095},"rotation":{"x":0.08399077504873276,"y":0.9266085624694824,"z":-0.24220500886440278,"w":0.2859249711036682},"size":5.911303997039795,"orthographic":false}